clonebuildregister/__init__.py
clonebuildregister/__main__.py
clonebuildregister/_version.py
clonebuildregister/build_image.py
clonebuildregister/clone_repo.py
clonebuildregister/clonebuildregister.py
clonebuildregister/exceptions.py
clonebuildregister/register_image.py
clonebuildregister-0.0.7.dist-info/LICENSE
clonebuildregister-0.0.7.dist-info/METADATA
clonebuildregister-0.0.7.dist-info/WHEEL
clonebuildregister-0.0.7.dist-info/entry_points.txt
clonebuildregister-0.0.7.dist-info/top_level.txt
clonebuildregister-0.0.7.dist-info/RECORD
