Metadata-Version: 2.1
Name: clonebuildregister
Version: 0.0.7
Summary: A package to clone a Git repository, build it's image using Docker, and then register it to the Google Artifact Registry.
Author-email: Jude Sproul <judesproul@gmail.com>, Chris Calloway <cbc@unc.edu>
License: BSD 3-Clause License
Project-URL: Homepage, https://github.com/cznethub/clonebuildregister
Project-URL: Issues, https://github.com/cznethub/clonebuildregister/issues
Keywords: docker,google cloud,artifact registry,build,clone,git,register,upload,image
Classifier: Development Status :: 4 - Beta
Classifier: Programming Language :: Python :: 3
Classifier: Programming Language :: Python :: 3 :: Only
Classifier: Programming Language :: Python :: 3.8
Classifier: Programming Language :: Python :: 3.9
Classifier: Programming Language :: Python :: 3.10
Classifier: Programming Language :: Python :: 3.11
Classifier: Programming Language :: Python :: 3.12
Requires-Python: >=3.8
License-File: LICENSE
Requires-Dist: docker
Requires-Dist: gitpython
Requires-Dist: github3.py
Requires-Dist: python-dotenv
Requires-Dist: google-cloud-artifact-registry
Requires-Dist: grpcio-status
Provides-Extra: dev
Requires-Dist: tox ; extra == 'dev'
Requires-Dist: pytest ; extra == 'dev'
